tortoiseschema/__init__.py
tortoiseschema-0.1.0.dist-info/WHEEL
tortoiseschema-0.1.0.dist-info/METADATA
tortoiseschema-0.1.0.dist-info/RECORD
