Metadata-Version: 2.1
Name: tortoiseschema
Version: 0.1.0
Summary: Tortoise ORM combined with pydantic
Author: Stanislav Zmiev
Author-email: szmiev2000@gmail.com
Requires-Python: >=3.8,<4.0
Classifier: Programming Language :: Python :: 3
Classifier: Programming Language :: Python :: 3.8
Classifier: Programming Language :: Python :: 3.9
Classifier: Programming Language :: Python :: 3.10
Classifier: Programming Language :: Python :: 3.11
